.travis.yml
LICENSE.txt
MANIFEST.in
README.md
README.rst
setup.cfg
setup.py
geopip/__init__.py
geopip/_geo_fkt.py
geopip/_geopip.py
geopip/_pure.py
geopip/_shapely.py
geopip/globe.geo.json
geopip.egg-info/PKG-INFO
geopip.egg-info/SOURCES.txt
geopip.egg-info/dependency_links.txt
geopip.egg-info/requires.txt
geopip.egg-info/top_level.txt
tests/conftest.py
tests/requirements.txt
tests/sample.geo.json
tests/test_geo_fkt.py
tests/test_geopip.py
tests/test_pure.py
tests/test_shapely.py