Metadata-Version: 1.1
Name: geopip
Version: 1.1
Summary: Reverse geocode a lng/lat coordinate within a geojson FeatureCollection.
Home-page: https://github.com/tammoippen/geopip
Author: Tammo Ippen
Author-email: tammo.ippen@posteo.de
License: MIT
Download-URL: https://github.com/tammoippen/geopip/archive/v1.1.tar.gz
Keywords: geojson,point in polygon,reverse geocode,countries
Platform: UNKNOWN
Classifier: License :: OSI Approved :: MIT License
Classifier: Programming Language :: Python
Classifier: Programming Language :: Python :: 2.7
Classifier: Programming Language :: Python :: 3
Classifier: Programming Language :: Python :: 3.5
Classifier: Programming Language :: Python :: 3.6
Classifier: Programming Language :: Python :: Implementation :: CPython
Classifier: Programming Language :: Python :: Implementation :: PyPy
